keyrock_hcs/__init__.py
keyrock_hcs/hcs/__init__.py
keyrock_hcs/hcs/datastore.py
keyrock_hcs/hcs/exc.py
keyrock_hcs/hcs/hcs.py
keyrock_hcs/hcs/hcs_object.py
keyrock_hcs/hcs/schema.py
keyrock_hcs/hcs/settings.py
keyrock_hcs/hcs/test_hcs.py
keyrock_hcs-2023.2.20.1654.dist-info/METADATA
keyrock_hcs-2023.2.20.1654.dist-info/WHEEL
keyrock_hcs-2023.2.20.1654.dist-info/top_level.txt
keyrock_hcs-2023.2.20.1654.dist-info/RECORD
